MANIFEST.in
README.rst
metadata.py
setup.py
dploi_fabric/__init__.py
dploi_fabric/buildout.py
dploi_fabric/celery.py
dploi_fabric/conf.py
dploi_fabric/django_utils.py
dploi_fabric/git.py
dploi_fabric/github.py
dploi_fabric/messages.py
dploi_fabric/newrelic.py
dploi_fabric/nginx.py
dploi_fabric/project.py
dploi_fabric/redis.py
dploi_fabric/solr.py
dploi_fabric/south.py
dploi_fabric/supervisor.py
dploi_fabric/tests.py
dploi_fabric/utils.py
dploi_fabric/virtualenv.py
dploi_fabric.egg-info/PKG-INFO
dploi_fabric.egg-info/SOURCES.txt
dploi_fabric.egg-info/dependency_links.txt
dploi_fabric.egg-info/not-zip-safe
dploi_fabric.egg-info/requires.txt
dploi_fabric.egg-info/top_level.txt
dploi_fabric/db/__init__.py
dploi_fabric/db/base.py
dploi_fabric/db/mysql.py
dploi_fabric/db/pg.py
dploi_fabric/templates/nginx/nginx.conf
dploi_fabric/templates/redis/redis.conf
dploi_fabric/templates/supervisor/celerycam_command
dploi_fabric/templates/supervisor/celeryd_command
dploi_fabric/templates/supervisor/gunicorn_command
dploi_fabric/templates/supervisor/supervisor-group.conf
dploi_fabric/templates/supervisor/supervisor.conf
dploi_fabric/templates/supervisor/supervisord.conf
dploi_fabric/toolbox/__init__.py
dploi_fabric/toolbox/datastructures.py
dploi_fabric/toolbox/logger.py
dploi_fabric/toolbox/template.py