Metadata-Version: 1.1
Name: dploi-fabric
Version: 0.2.1
Summary: A collection of fabric tasks
Home-page: http://github.com/dploi/dploi-fabric
Author: Benjamin Wohlwend, Kristian Oellegaard, Stefan Foulis
Author-email: developers@divio.ch
License: TBA
Platform: OS Independent
Classifier: Development Status :: 4 - Beta
Classifier: Framework :: Django
Classifier: Intended Audience :: Developers
Classifier: License :: OSI Approved :: BSD License
Classifier: Operating System :: OS Independent
Classifier: Programming Language :: Python
Classifier: Topic :: Internet :: WWW/HTTP
